mindspore_rec/__init__.py
mindspore_rec/ops/__init__.py
mindspore_rec/ops/embedding.py
mindspore_rec/train/__init__.py
mindspore_rec/train/rec_model.py
mindspore_rec-0.3.0.dist-info/LICENSE
mindspore_rec-0.3.0.dist-info/METADATA
mindspore_rec-0.3.0.dist-info/WHEEL
mindspore_rec-0.3.0.dist-info/top_level.txt
mindspore_rec-0.3.0.dist-info/RECORD
